LICENSE
MANIFEST.in
README.rst
changelog.rst
setup.py
examples/bar_example.py
examples/basic.py
examples/basic_single_annotation.py
examples/change_popup_color.py
examples/contour_example.py
examples/customize_keyboard_shortcuts.py
examples/date_example.py
examples/draggable_example.py
examples/highlighting_example.py
examples/hover_example.py
examples/image_example.py
examples/labeled_points_example.py
examples/multi_highlight_example.py
examples/scatter_example.py
examples/show_artist_labels.py
mpldatacursor/__init__.py
mpldatacursor/convenience.py
mpldatacursor/datacursor.py
mpldatacursor/pick_info.py
mpldatacursor_rcognita.egg-info/PKG-INFO
mpldatacursor_rcognita.egg-info/SOURCES.txt
mpldatacursor_rcognita.egg-info/dependency_links.txt
mpldatacursor_rcognita.egg-info/requires.txt
mpldatacursor_rcognita.egg-info/top_level.txt