Metadata-Version: 2.1
Name: mpldatacursor-rcognita
Version: 0.7.2
Summary: Interactive data cursors for Matplotlib
Home-page: https://github.com/joferkington/mpldatacursor/
Author: Joe Kington
Author-email: joferkington@gmail.com
License: MIT
Platform: UNKNOWN
